tg_ops/__init__.py
tg_ops/bot/__init__.py
tg_ops/bot/app_runner.py
tg_ops/bot/commands/executors.py
tg_ops/bot/commands/services.py
tg_ops/bot/handlers.py
tg_ops/bot/ui/menus.py
tg_ops/bot/webhook.py
tg_ops/config.py
tg_ops/main.py
tg_ops-0.1.0.dist-info/METADATA
tg_ops-0.1.0.dist-info/WHEEL
tg_ops-0.1.0.dist-info/entry_points.txt
tg_ops-0.1.0.dist-info/licenses/LICENSE
tg_ops-0.1.0.dist-info/RECORD
