Metadata-Version: 2.4
Name: tg-ops
Version: 0.1.0
Summary: A secure Telegram bot for remote system operations and monitoring on Linux hosts
License: MIT
License-File: LICENSE
Keywords: telegram,bot,monitoring,linux,devops,remote-control
Author: Idir Oura
Author-email: idir.oura@protonmail.com
Requires-Python: >=3.11
Classifier: Environment :: Console
Classifier: Intended Audience :: Developers
Classifier: Intended Audience :: System Administrators
Classifier: License :: OSI Approved :: MIT License
Classifier: Operating System :: POSIX :: Linux
Classifier: Programming Language :: Python :: 3.11
Classifier: Programming Language :: Python :: 3.12
Classifier: Programming Language :: Python :: 3.13
Classifier: Programming Language :: Python :: 3.14
Classifier: Topic :: System :: Monitoring
Classifier: Topic :: System :: Systems Administration
Requires-Dist: docker (>=7.1.0,<8.0.0)
Requires-Dist: psutil (>=7.2.1)
Requires-Dist: python-telegram-bot[webhooks] (>=22.3,<23.0)
Requires-Dist: requests (>=2.32.5,<3.0.0)
Project-URL: Homepage, https://github.com/idirxv/tg-ops
Project-URL: Repository, https://github.com/idirxv/tg-ops
